MarkovChainMonteCarloFoundationsApplicationsLectureNotesUcbCs294/README.md
MarkovChainMonteCarloFoundationsApplicationsLectureNotesUcbCs294/__init__.py
MarkovChainMonteCarloFoundationsApplicationsLectureNotesUcbCs294/__main__.py
MarkovChainMonteCarloFoundationsApplicationsLectureNotesUcbCs294/file.pdf
MarkovChainMonteCarloFoundationsApplicationsLectureNotesUcbCs294/index.html
markov_chain_monte_carlo_foundations_applications_lecture_notes_ucb_cs294-2024.3.2.0.dist-info/METADATA
markov_chain_monte_carlo_foundations_applications_lecture_notes_ucb_cs294-2024.3.2.0.dist-info/WHEEL
markov_chain_monte_carlo_foundations_applications_lecture_notes_ucb_cs294-2024.3.2.0.dist-info/entry_points.txt
markov_chain_monte_carlo_foundations_applications_lecture_notes_ucb_cs294-2024.3.2.0.dist-info/top_level.txt
markov_chain_monte_carlo_foundations_applications_lecture_notes_ucb_cs294-2024.3.2.0.dist-info/RECORD
